missing_values/__init__.py
missing_values/missing_values.py
missing_values_101703283-0.1.3.dist-info/LICENSE.txt
missing_values_101703283-0.1.3.dist-info/METADATA
missing_values_101703283-0.1.3.dist-info/WHEEL
missing_values_101703283-0.1.3.dist-info/entry_points.txt
missing_values_101703283-0.1.3.dist-info/top_level.txt
missing_values_101703283-0.1.3.dist-info/RECORD
